.DS_Store
meeglet/__init__.py
meeglet/_modidx.py
meeglet-0.0.1.dist-info/LICENSE
meeglet-0.0.1.dist-info/METADATA
meeglet-0.0.1.dist-info/WHEEL
meeglet-0.0.1.dist-info/entry_points.txt
meeglet-0.0.1.dist-info/top_level.txt
meeglet-0.0.1.dist-info/RECORD
