Metadata-Version: 2.1
Name: meeglet
Version: 0.0.1
Summary: Morlet Wavelets for M/EEG analysis
Home-page: https://github.com/Roche/neuro-meeglet
Author: dengemann
Author-email: denis.engemann@gmail.com
License: Apache Software License 2.0
Keywords: MEG EEG wavelets Morlet signal analysis
Classifier: Development Status :: 4 - Beta
Classifier: Intended Audience :: Developers
Classifier: Natural Language :: English
Classifier: Programming Language :: Python :: 3.10
Classifier: License :: OSI Approved :: Apache Software License
Requires-Python: >=3.10
License-File: LICENSE
Requires-Dist: mne[data]>=1.3
Requires-Dist: numpy
Requires-Dist: scipy
Requires-Dist: matplotlib
Requires-Dist: pandas
Provides-Extra: dev
Requires-Dist: nbdev>=2.3; extra == "dev"
Requires-Dist: mne[data]>=1.3; extra == "dev"
Requires-Dist: numpy; extra == "dev"
Requires-Dist: scipy; extra == "dev"
Requires-Dist: matplotlib; extra == "dev"
Requires-Dist: pandas; extra == "dev"
Requires-Dist: jupyter; extra == "dev"
Requires-Dist: jupyter-cache; extra == "dev"
Requires-Dist: ipykernel; extra == "dev"
Requires-Dist: nbdev-numpy; extra == "dev"
Requires-Dist: nbdev-scipy; extra == "dev"
Requires-Dist: nbdev-stdlib; extra == "dev"
Requires-Dist: nbdev-pandas; extra == "dev"
Requires-Dist: memory-profiler; extra == "dev"
